webtogit/__init__.py
webtogit/cli.py
webtogit/core.py
webtogit/release.py
webtogit/util.py
webtogit-0.1.1.dist-info/licenses/LICENSE
webtogit-0.1.1.dist-info/METADATA
webtogit-0.1.1.dist-info/WHEEL
webtogit-0.1.1.dist-info/entry_points.txt
webtogit-0.1.1.dist-info/top_level.txt
webtogit-0.1.1.dist-info/RECORD
