Metadata-Version: 2.4
Name: webtogit
Version: 0.1.1
Summary: simple tool to download etherpads and archive them in a git repository
Author: Carsten Knoll
Author-email: firstname.lastname@posteo.de
License: GPLv3
Classifier: Development Status :: 3 - Alpha
Classifier: Intended Audience :: Developers
Classifier: License :: OSI Approved :: GNU General Public License v3 (GPLv3)
Classifier: Programming Language :: Python :: 3
License-File: LICENSE
Requires-Dist: pyyaml
Requires-Dist: gitpython
Requires-Dist: appdirs
Requires-Dist: ipydex
Requires-Dist: colorama
Requires-Dist: requests
Requires-Dist: tqdm
Dynamic: author
Dynamic: author-email
Dynamic: classifier
Dynamic: description
Dynamic: license
Dynamic: license-file
Dynamic: requires-dist
Dynamic: summary
